gdpr_manager/__init__.py
gdpr_manager/admin.py
gdpr_manager/apps.py
gdpr_manager/handlers.py
gdpr_manager/helpers.py
gdpr_manager/models.py
gdpr_manager/registry.py
gdpr_manager/settings.py
gdpr_manager/migrations/0001_initial.py
gdpr_manager/migrations/__init__.py
gdpr_manager/templates/gdpr_manager/admin/gm_change_list.html
hubble_django_gdpr_manager-0.1.0.dist-info/METADATA
hubble_django_gdpr_manager-0.1.0.dist-info/WHEEL
hubble_django_gdpr_manager-0.1.0.dist-info/licenses/LICENSE
hubble_django_gdpr_manager-0.1.0.dist-info/RECORD
