Metadata-Version: 2.3
Name: hubble_django_gdpr_manager
Version: 0.1.0
Author-email: Hubble <developers@hubblehq.com>
License-File: LICENSE
Requires-Python: >=3.9
Requires-Dist: django>4.2
